sniffing/spi.vhd
library IEEE;
use IEEE.STD_LOGIC_1164.ALL;
use IEEE.NUMERIC_STD.ALL;

entity spi is
    Port (
        clk         : in  std_logic;              -- System clock (e.g., 50 MHz)
        reset       : in  std_logic;
        sclk        : in  std_logic;              -- SPI clock
        miso        : in  std_logic;
        mosi        : in  std_logic;
        cs          : in  std_logic;
        led_miso    : out std_logic;
        led_mosi    : out std_logic;
        led_cs      : out std_logic;
        -- Circular buffer output
        buffer_data     : out std_logic_vector(15 downto 0);  -- Expanded to 16 bits
        buffer_timestamp: out std_logic_vector(31 downto 0);
        buffer_addr     : out std_logic_vector(7 downto 0);
        buffer_wr       : out std_logic
    );
end spi;

architecture Behavioral of spi is
    -- Buffer entry: 16-bit data + 32-bit timestamp
    type spi_sample is record
        data      : std_logic_vector(15 downto 0);  -- Expanded to 16 bits
        timestamp : std_logic_vector(31 downto 0);
    end record;
    -- Circular buffer type
    type buffer_type is array (0 to 255) of spi_sample;
    signal circ_buffer : buffer_type;
    signal write_ptr : unsigned(7 downto 0) := (others => '0');
    
    -- Edge detection
    signal sclk_prev : std_logic := '0';
    signal sclk_rising : std_logic := '0';
    
    -- Frequency measurement
    signal sclk_counter : unsigned(31 downto 0) := (others => '0');
    signal sclk_period  : unsigned(31 downto 0) := (others => '0');
    
    -- Timestamp counter
    signal timestamp_counter : unsigned(31 downto 0) := (others => '0');
    
    -- Sampled SPI values
    signal miso_reg, mosi_reg, cs_reg : std_logic;
    
    -- Frequency calculation signals
    signal system_clk_freq : unsigned(31 downto 0) := to_unsigned(50000000, 32);  -- Assuming 50 MHz system clock
    signal calculated_freq : unsigned(31 downto 0) := (others => '0');           -- Frequency in Hz
    signal freq_hz        : unsigned(12 downto 0) := (others => '0');           -- Frequency in Hz for buffer
begin
    process(clk)
    begin
        if rising_edge(clk) then
            if reset = '0' then
                write_ptr         <= (others => '0');
                sclk_counter      <= (others => '0');
                sclk_period       <= (others => '0');
                timestamp_counter <= (others => '0');
                sclk_prev         <= '0';
                buffer_wr         <= '0';
                sclk_rising       <= '0';
                calculated_freq   <= (others => '0');
                freq_hz           <= (others => '0');
            else
                -- Timestamp increment
                timestamp_counter <= timestamp_counter + 1;
                
                -- Default state
                buffer_wr <= '0';
                sclk_rising <= '0';
                
                -- SCLK edge detection
                if sclk = '1' and sclk_prev = '0' then
                    -- Rising edge detected
                    sclk_rising <= '1';
                    -- Store frequency
                    sclk_period  <= sclk_counter;
                    sclk_counter <= (others => '0');
                else
                    sclk_counter <= sclk_counter + 1;
                end if;
                sclk_prev <= sclk;
                
                -- Calculate actual frequency in Hz
                -- Frequency = System clock frequency / Period
                if sclk_period > 0 and sclk_period < system_clk_freq then
                    calculated_freq <= system_clk_freq / sclk_period;
                    -- Convert to 100 kHz units (divide by 100,000)
                    -- Integer division by 100,000 is equivalent to shifting right by 16.61 bits
                    -- We'll use a 17-bit shift for simplicity and efficiency (divide by 131,072)
                    freq_hz <= resize(calculated_freq(31 downto 17), 13);
                else
                    calculated_freq <= (others => '0');
                    freq_hz <= (others => '0');
                end if;
                
                -- On SCLK rising edge
                if sclk_rising = '1' then
                    -- Sample SPI lines
                    miso_reg <= miso;
                    mosi_reg <= mosi;
                    cs_reg   <= cs;
                    
                    -- Update LEDs
                    led_miso <= miso;
                    led_mosi <= mosi;
                    led_cs   <= cs;
                    
                    -- Create and store sample
                    -- Format: First 3 bits for SPI signals, remaining 13 bits for frequency in Hz
                    circ_buffer(to_integer(write_ptr)).data      <= miso & mosi & cs & std_logic_vector(freq_hz);
                    circ_buffer(to_integer(write_ptr)).timestamp <= std_logic_vector(timestamp_counter);
                    
                    -- Output buffer values for UART/reader
                    buffer_data      <= miso & mosi & cs & std_logic_vector(freq_hz);
                    buffer_timestamp <= std_logic_vector(timestamp_counter);
                    buffer_addr      <= std_logic_vector(write_ptr);
                    buffer_wr        <= '1';
                    
                    -- Advance circular buffer pointer
                    write_ptr <= write_ptr + 1;
                end if;
            end if;
        end if;
    end process;
end Behavioral;

sniffing/spi_tb.vhd
library IEEE;
use IEEE.STD_LOGIC_1164.ALL;
use IEEE.NUMERIC_STD.ALL;

entity spi_tb is
-- Empty entity for testbench
end spi_tb;

architecture Behavioral of spi_tb is
    -- Component declaration for the Unit Under Test (UUT)
    component spi
        Port (
            clk         : in  std_logic;
            reset       : in  std_logic;
            sclk        : in  std_logic;
            miso        : in  std_logic;
            mosi        : in  std_logic;
            cs          : in  std_logic;
            led_miso    : out std_logic;
            led_mosi    : out std_logic;
            led_cs      : out std_logic;
            buffer_data     : out std_logic_vector(15 downto 0);  -- Updated to 16 bits
            buffer_timestamp: out std_logic_vector(31 downto 0);
            buffer_addr     : out std_logic_vector(7 downto 0);
            buffer_wr       : out std_logic
        );
    end component;
    
    -- Testbench constants
    constant CLK_PERIOD : time := 20 ns;        -- 50 MHz system clock
    constant SCLK_PERIOD : time := 200 ns;      -- 5 MHz SPI clock (typical)
    
    -- Testbench signals
    signal clk_tb          : std_logic := '0';
    signal reset_tb        : std_logic := '0';
    signal sclk_tb         : std_logic := '0';
    signal miso_tb         : std_logic := '0';
    signal mosi_tb         : std_logic := '0';
    signal cs_tb           : std_logic := '1';  -- CS active low, initially inactive
    
    -- Output signals
    signal led_miso_tb     : std_logic;
    signal led_mosi_tb     : std_logic;
    signal led_cs_tb       : std_logic;
    signal buffer_data_tb  : std_logic_vector(15 downto 0);  -- Updated to 16 bits
    signal buffer_timestamp_tb : std_logic_vector(31 downto 0);
    signal buffer_addr_tb  : std_logic_vector(7 downto 0);
    signal buffer_wr_tb    : std_logic;
    
    -- SPI test data
    type test_data_array is array (natural range <>) of std_logic_vector(7 downto 0);
    constant test_data : test_data_array := (
        X"A5",  -- 10100101
        X"3C",  -- 00111100
        X"F0"   -- 11110000
    );
    
    -- Function to convert std_logic_vector to hex string
    function to_hex_string(slv: std_logic_vector) return string is
        variable result: string(1 to slv'length/4);
        variable v: std_logic_vector(3 downto 0);
        variable c: character;
    begin
        for i in result'range loop
            v := slv((i*4)-1 downto (i-1)*4);
            case v is
                when "0000" => c := '0';
                when "0001" => c := '1';
                when "0010" => c := '2';
                when "0011" => c := '3';
                when "0100" => c := '4';
                when "0101" => c := '5';
                when "0110" => c := '6';
                when "0111" => c := '7';
                when "1000" => c := '8';
                when "1001" => c := '9';
                when "1010" => c := 'A';
                when "1011" => c := 'B';
                when "1100" => c := 'C';
                when "1101" => c := 'D';
                when "1110" => c := 'E';
                when "1111" => c := 'F';
                when others => c := 'X';
            end case;
            result(i) := c;
        end loop;
        return result;
    end function;
    
    -- Function to extract SPI signals and frequency from buffer data
    function decode_buffer_data(data: std_logic_vector(15 downto 0)) return string is
        variable miso_val : std_logic := data(15);
        variable mosi_val : std_logic := data(14);
        variable cs_val : std_logic := data(13);
        variable freq_100khz : integer := to_integer(unsigned(data(12 downto 0)));
        variable freq_khz : integer := freq_100khz * 100;
    begin
        return "MISO=" & std_logic'image(miso_val) & 
               ", MOSI=" & std_logic'image(mosi_val) & 
               ", CS=" & std_logic'image(cs_val) & 
               ", Freq=" & integer'image(freq_khz) & " kHz (" & 
               integer'image(freq_khz / 1000) & "." & 
               integer'image((freq_khz mod 1000) / 100) & " MHz)";
    end function;
    
    -- Additional variables for test cases with varying SPI clock frequencies
    signal sclk_divider : integer := 5;  -- Initially 5 MHz (50 MHz / 10)
    
    -- Simulation control
    signal sim_done : boolean := false;
    
begin
    -- Instantiate the Unit Under Test (UUT)
    uut: spi
    port map (
        clk => clk_tb,
        reset => reset_tb,
        sclk => sclk_tb,
        miso => miso_tb,
        mosi => mosi_tb,
        cs => cs_tb,
        led_miso => led_miso_tb,
        led_mosi => led_mosi_tb,
        led_cs => led_cs_tb,
        buffer_data => buffer_data_tb,
        buffer_timestamp => buffer_timestamp_tb,
        buffer_addr => buffer_addr_tb,
        buffer_wr => buffer_wr_tb
    );
    
    -- Clock generation process for system clock
    clk_process: process
    begin
        while not sim_done loop
            clk_tb <= '0';
            wait for CLK_PERIOD/2;
            clk_tb <= '1';
            wait for CLK_PERIOD/2;
        end loop;
        wait;
    end process;
    
    -- Dynamic SPI Clock generation process
    -- Now with variable frequency for testing frequency detection
    spi_clk_process: process
        variable sclk_half_period : time;
    begin
        while not sim_done loop
            sclk_half_period := (CLK_PERIOD * sclk_divider) / 2;
            sclk_tb <= '0';
            wait for sclk_half_period;
            sclk_tb <= '1';
            wait for sclk_half_period;
        end loop;
        wait;
    end process;
    
    -- Stimulus process
    stim_proc: process
    begin
        -- Initial reset
        reset_tb <= '0';  -- Active low reset
        wait for 100 ns;
        reset_tb <= '1';  -- Release reset
        wait for 100 ns;
        
        -- Test Case 1: Send multiple bytes through SPI at 5 MHz
        report "Test Case 1: SPI Transfer at 5 MHz";
        sclk_divider <= 5;  -- 50 MHz / 5 = 10 MHz
        wait for 200 ns;    -- Wait for clock stabilization
        
        for byte_idx in test_data'range loop
            -- Start SPI transaction (CS active low)
            cs_tb <= '0';
            wait for SCLK_PERIOD;
            
            -- Send 8 bits MSB first
            for bit_idx in 7 downto 0 loop
                -- Set MOSI based on test data
                mosi_tb <= test_data(byte_idx)(bit_idx);
                
                -- Set MISO to inverse of MOSI for simple test pattern
                miso_tb <= not test_data(byte_idx)(bit_idx);
                
                -- Wait for a full SCLK cycle
                wait for SCLK_PERIOD;
            end loop;
            
            -- End transaction with CS high
            cs_tb <= '1';
            wait for SCLK_PERIOD * 2;
        end loop;
        
        -- Test Case 2: Check frequency detection at 1 MHz
        report "Test Case 2: SPI Transfer at 1 MHz";
        sclk_divider <= 25;  -- 50 MHz / 25 = 2 MHz
        wait for 1 us;      -- Wait for clock stabilization
        
        cs_tb <= '0';
        
        for i in 0 to 15 loop
            -- Alternate MOSI for a simple pattern
            mosi_tb <= not mosi_tb;
            
            -- MISO with a different pattern
            if i mod 2 = 0 then
                miso_tb <= not miso_tb;
            end if;
            
            wait for SCLK_PERIOD * 5;  -- Adjusted for slower clock
        end loop;
        
        cs_tb <= '1';
        wait for SCLK_PERIOD * 5;
        
        -- Test Case 3: Check frequency detection at 10 MHz
        report "Test Case 3: SPI Transfer at 10 MHz";
        sclk_divider <= 2;  -- 50 MHz / 2 = 25 MHz
        wait for 1 us;      -- Wait for clock stabilization
        
        cs_tb <= '0';
        for i in 0 to 7 loop
            mosi_tb <= not mosi_tb;
            miso_tb <= not miso_tb;
            wait for SCLK_PERIOD / 2;  -- Adjusted for faster clock
        end loop;
        cs_tb <= '1';
        wait for SCLK_PERIOD;
        
        -- Test Case 4: Reset during transfer
        report "Test Case 4: Reset during transfer";
        sclk_divider <= 5;  -- Back to original speed
        wait for 1 us;
        
        cs_tb <= '0';
        mosi_tb <= '1';
        miso_tb <= '0';
        wait for SCLK_PERIOD * 3;
        
        -- Apply reset in the middle of transaction
        reset_tb <= '0';
        wait for SCLK_PERIOD * 2;
        reset_tb <= '1';
        wait for SCLK_PERIOD * 2;
        
        -- Continue with transfer
        for i in 0 to 7 loop
            mosi_tb <= not mosi_tb;
            wait for SCLK_PERIOD;
        end loop;
        
        cs_tb <= '1';
        wait for SCLK_PERIOD * 4;
        
        -- End simulation
        sim_done <= true;
        wait for 100 ns;
        
        report "Simulation completed successfully";
        wait;
    end process;
    
    -- Monitor process to check output signals
    monitor_proc: process
    begin
        wait until rising_edge(clk_tb);
        
        if buffer_wr_tb = '1' then
            report "Buffer Write: Address = " & 
                   integer'image(to_integer(unsigned(buffer_addr_tb))) & 
                   ", Data = 0x" & to_hex_string(buffer_data_tb) & 
                   ", " & decode_buffer_data(buffer_data_tb) &
                   ", Timestamp = " & integer'image(to_integer(unsigned(buffer_timestamp_tb)));
        end if;
        
        if sim_done then
            wait;
        end if;
    end process;
    
end Behavioral;

sniffing/spi_simulation.vcd
$date
  Tue Apr 15 13:31:12 2025
$end
$version
  GHDL v0
$end
$timescale
  1 fs
$end
$scope module standard $end
$upscope $end
$scope module std_logic_1164 $end
$upscope $end
$scope module numeric_std $end
$upscope $end
$scope module spi_tb $end
$var reg 1 ! clk_tb $end
$var reg 1 " reset_tb $end
$var reg 1 # sclk_tb $end
$var reg 1 $ miso_tb $end
$var reg 1 % mosi_tb $end
$var reg 1 & cs_tb $end
$var reg 1 ' led_miso_tb $end
$var reg 1 ( led_mosi_tb $end
$var reg 1 ) led_cs_tb $end
$var reg 16 * buffer_data_tb[15:0] $end
$var reg 32 + buffer_timestamp_tb[31:0] $end
$var reg 8 , buffer_addr_tb[7:0] $end
$var reg 1 - buffer_wr_tb $end
$var integer 32 . sclk_divider $end
$var reg 1 / sim_done $end
$scope module uut $end
$var reg 1 0 clk $end
$var reg 1 1 reset $end
$var reg 1 2 sclk $end
$var reg 1 3 miso $end
$var reg 1 4 mosi $end
$var reg 1 5 cs $end
$var reg 1 6 led_miso $end
$var reg 1 7 led_mosi $end
$var reg 1 8 led_cs $end
$var reg 16 9 buffer_data[15:0] $end
$var reg 32 : buffer_timestamp[31:0] $end
$var reg 8 ; buffer_addr[7:0] $end
$var reg 1 < buffer_wr $end
$comment circ_buffer is not handled $end
$var reg 8 = write_ptr[7:0] $end
$var reg 1 > sclk_prev $end
$var reg 1 ? sclk_rising $end
$var reg 32 @ sclk_counter[31:0] $end
$var reg 32 A sclk_period[31:0] $end
$var reg 32 B timestamp_counter[31:0] $end
$var reg 1 C miso_reg $end
$var reg 1 D mosi_reg $end
$var reg 1 E cs_reg $end
$var reg 32 F system_clk_freq[31:0] $end
$var reg 32 G calculated_freq[31:0] $end
$var reg 13 H freq_hz[12:0] $end
$upscope $end
$upscope $end
$enddefinitions $end
#0
0!
0"
0#
0$
0%
1&
U'
U(
U)
bUUUUUUUUUUUUUUUU *
bUUUUUUUUUUUUUUUUUUUUUUUUUUUUUUUU +
bUUUUUUUU ,
U-
b101 .
0/
00
01
02
03
04
15
U6
U7
U8
bUUUUUUUUUUUUUUUU 9
bUUUUUUUUUUUUUUUUUUUUUUUUUUUUUUUU :
bUUUUUUUU ;
U<
b00000000 =
0>
0?
b00000000000000000000000000000000 @
b00000000000000000000000000000000 A
b00000000000000000000000000000000 B
UC
UD
UE
b00000010111110101111000010000000 F
b00000000000000000000000000000000 G
b0000000000000 H
#10000000
1!
0-
10
0<
#20000000
0!
00
#30000000
1!
10
#40000000
0!
00
#50000000
1!
1#
10
12
#60000000
0!
00
#70000000
1!
10
#80000000
0!
00
#90000000
1!
10
#100000000
0!
1"
0#
00
11
02
#110000000
1!
10
b00000000000000000000000000000001 @
b00000000000000000000000000000001 B
#120000000
0!
00
#130000000
1!
10
b00000000000000000000000000000010 @
b00000000000000000000000000000010 B
#140000000
0!
00
#150000000
1!
1#
10
12
1>
1?
b00000000000000000000000000000000 @
b00000000000000000000000000000010 A
b00000000000000000000000000000011 B
#160000000
0!
00
#170000000
1!
0'
0(
1)
b0010000000000000 *
b00000000000000000000000000000011 +
b00000000 ,
1-
10
06
07
18
b0010000000000000 9
b00000000000000000000000000000011 :
b00000000 ;
1<
b00000001 =
0?
b00000000000000000000000000000001 @
b00000000000000000000000000000100 B
0C
0D
1E
b00000001011111010111100001000000 G
#180000000
0!
00
#190000000
1!
0-
10
0<
b00000000000000000000000000000010 @
b00000000000000000000000000000101 B
b0000010111110 H
#200000000
0!
0#
00
02
#210000000
1!
10
0>
b00000000000000000000000000000011 @
b00000000000000000000000000000110 B
#220000000
0!
00
#230000000
1!
10
b00000000000000000000000000000100 @
b00000000000000000000000000000111 B
#240000000
0!
00
#250000000
1!
1#
10
12
1>
1?
b00000000000000000000000000000000 @
b00000000000000000000000000000100 A
b00000000000000000000000000001000 B
#260000000
0!
00
#270000000
1!
b0010000010111110 *
b00000000000000000000000000001000 +
b00000001 ,
1-
10
b0010000010111110 9
b00000000000000000000000000001000 :
b00000001 ;
1<
b00000010 =
0?
b00000000000000000000000000000001 @
b00000000000000000000000000001001 B
b00000000101111101011110000100000 G
#280000000
0!
00
#290000000
1!
0-
10
0<
b00000000000000000000000000000010 @
b00000000000000000000000000001010 B
b0000001011111 H
#300000000
0!
0#
00
02
#310000000
1!
10
0>
b00000000000000000000000000000011 @
b00000000000000000000000000001011 B
#320000000
0!
00
#330000000
1!
10
b00000000000000000000000000000100 @
b00000000000000000000000000001100 B
#340000000
0!
00
#350000000
1!
1#
10
12
1>
1?
b00000000000000000000000000000000 @
b00000000000000000000000000001101 B
#360000000
0!
00
#370000000
1!
b0010000001011111 *
b00000000000000000000000000001101 +
b00000010 ,
1-
10
b0010000001011111 9
b00000000000000000000000000001101 :
b00000010 ;
1<
b00000011 =
0?
b00000000000000000000000000000001 @
b00000000000000000000000000001110 B
#380000000
0!
00
#390000000
1!
0-
10
0<
b00000000000000000000000000000010 @
b00000000000000000000000000001111 B
#400000000
0!
0#
0&
00
02
05
#410000000
1!
10
0>
b00000000000000000000000000000011 @
b00000000000000000000000000010000 B
#420000000
0!
00
#430000000
1!
10
b00000000000000000000000000000100 @
b00000000000000000000000000010001 B
#440000000
0!
00
#450000000
1!
1#
10
12
1>
1?
b00000000000000000000000000000000 @
b00000000000000000000000000010010 B
#460000000
0!
00
#470000000
1!
0)
b0000000001011111 *
b00000000000000000000000000010010 +
b00000011 ,
1-
10
08
b0000000001011111 9
b00000000000000000000000000010010 :
b00000011 ;
1<
b00000100 =
0?
b00000000000000000000000000000001 @
b00000000000000000000000000010011 B
0E
#480000000
0!
00
#490000000
1!
0-
10
0<
b00000000000000000000000000000010 @
b00000000000000000000000000010100 B
#500000000
0!
0#
00
02
#510000000
1!
10
0>
b00000000000000000000000000000011 @
b00000000000000000000000000010101 B
#520000000
0!
00
#530000000
1!
10
b00000000000000000000000000000100 @
b00000000000000000000000000010110 B
#540000000
0!
00
#550000000
1!
1#
10
12
1>
1?
b00000000000000000000000000000000 @
b00000000000000000000000000010111 B
#560000000
0!
00
#570000000
1!
b00000000000000000000000000010111 +
b00000100 ,
1-
10
b00000000000000000000000000010111 :
b00000100 ;
1<
b00000101 =
0?
b00000000000000000000000000000001 @
b00000000000000000000000000011000 B
#580000000
0!
00
#590000000
1!
0-
10
0<
b00000000000000000000000000000010 @
b00000000000000000000000000011001 B
#600000000
0!
0#
1%
00
02
14
#610000000
1!
10
0>
b00000000000000000000000000000011 @
b00000000000000000000000000011010 B
#620000000
0!
00
#630000000
1!
10
b00000000000000000000000000000100 @
b00000000000000000000000000011011 B
#640000000
0!
00
#650000000
1!
1#
10
12
1>
1?
b00000000000000000000000000000000 @
b00000000000000000000000000011100 B
#660000000
0!
00
#670000000
1!
1(
b0100000001011111 *
b00000000000000000000000000011100 +
b00000101 ,
1-
10
17
b0100000001011111 9
b00000000000000000000000000011100 :
b00000101 ;
1<
b00000110 =
0?
b00000000000000000000000000000001 @
b00000000000000000000000000011101 B
1D
#680000000
0!
00
#690000000
1!
0-
10
0<
b00000000000000000000000000000010 @
b00000000000000000000000000011110 B
#700000000
0!
0#
00
02
#710000000
1!
10
0>
b00000000000000000000000000000011 @
b00000000000000000000000000011111 B
#720000000
0!
00
#730000000
1!
10
b00000000000000000000000000000100 @
b00000000000000000000000000100000 B
#740000000
0!
00
#750000000
1!
1#
10
12
1>
1?
b00000000000000000000000000000000 @
b00000000000000000000000000100001 B
#760000000
0!
00
#770000000
1!
b00000000000000000000000000100001 +
b00000110 ,
1-
10
b00000000000000000000000000100001 :
b00000110 ;
1<
b00000111 =
0?
b00000000000000000000000000000001 @
b00000000000000000000000000100010 B
#780000000
0!
00
#790000000
1!
0-
10
0<
b00000000000000000000000000000010 @
b00000000000000000000000000100011 B
#800000000
0!
0#
1$
0%
00
02
13
04
#810000000
1!
10
0>
b00000000000000000000000000000011 @
b00000000000000000000000000100100 B
#820000000
0!
00
#830000000
1!
10
b00000000000000000000000000000100 @
b00000000000000000000000000100101 B
#840000000
0!
00
#850000000
1!
1#
10
12
1>
1?
b00000000000000000000000000000000 @
b00000000000000000000000000100110 B
#860000000
0!
00
#870000000
1!
1'
0(
b1000000001011111 *
b00000000000000000000000000100110 +
b00000111 ,
1-
10
16
07
b1000000001011111 9
b00000000000000000000000000100110 :
b00000111 ;
1<
b00001000 =
0?
b00000000000000000000000000000001 @
b00000000000000000000000000100111 B
1C
0D
#880000000
0!
00
#890000000
1!
0-
10
0<
b00000000000000000000000000000010 @
b00000000000000000000000000101000 B
#900000000
0!
0#
00
02
#910000000
1!
10
0>
b00000000000000000000000000000011 @
b00000000000000000000000000101001 B
#920000000
0!
00
#930000000
1!
10
b00000000000000000000000000000100 @
b00000000000000000000000000101010 B
#940000000
0!
00
#950000000
1!
1#
10
12
1>
1?
b00000000000000000000000000000000 @
b00000000000000000000000000101011 B
#960000000
0!
00
#970000000
1!
b00000000000000000000000000101011 +
b00001000 ,
1-
10
b00000000000000000000000000101011 :
b00001000 ;
1<
b00001001 =
0?
b00000000000000000000000000000001 @
b00000000000000000000000000101100 B
#980000000
0!
00
#990000000
1!
0-
10
0<
b00000000000000000000000000000010 @
b00000000000000000000000000101101 B
#1000000000
0!
0#
0$
1%
00
02
03
14
#1010000000
1!
10
0>
b00000000000000000000000000000011 @
b00000000000000000000000000101110 B
#1020000000
0!
00
#1030000000
1!
10
b00000000000000000000000000000100 @
b00000000000000000000000000101111 B
#1040000000
0!
00
#1050000000
1!
1#
10
12
1>
1?
b00000000000000000000000000000000 @
b00000000000000000000000000110000 B
#1060000000
0!
00
#1070000000
1!
0'
1(
b0100000001011111 *
b00000000000000000000000000110000 +
b00001001 ,
1-
10
06
17
b0100000001011111 9
b00000000000000000000000000110000 :
b00001001 ;
1<
b00001010 =
0?
b00000000000000000000000000000001 @
b00000000000000000000000000110001 B
0C
1D
#1080000000
0!
00
#1090000000
1!
0-
10
0<
b00000000000000000000000000000010 @
b00000000000000000000000000110010 B
#1100000000
0!
0#
00
02
#1110000000
1!
10
0>
b00000000000000000000000000000011 @
b00000000000000000000000000110011 B
#1120000000
0!
00
#1130000000
1!
10
b00000000000000000000000000000100 @
b00000000000000000000000000110100 B
#1140000000
0!
00
#1150000000
1!
1#
10
12
1>
1?
b00000000000000000000000000000000 @
b00000000000000000000000000110101 B
#1160000000
0!
00
#1170000000
1!
b00000000000000000000000000110101 +
b00001010 ,
1-
10
b00000000000000000000000000110101 :
b00001010 ;
1<
b00001011 =
0?
b00000000000000000000000000000001 @
b00000000000000000000000000110110 B
#1180000000
0!
00
#1190000000
1!
0-
10
0<
b00000000000000000000000000000010 @
b00000000000000000000000000110111 B
#1200000000
0!
0#
1$
0%
00
02
13
04
#1210000000
1!
10
0>
b00000000000000000000000000000011 @
b00000000000000000000000000111000 B
#1220000000
0!
00
#1230000000
1!
10
b00000000000000000000000000000100 @
b00000000000000000000000000111001 B
#1240000000
0!
00
#1250000000
1!
1#
10
12
1>
1?
b00000000000000000000000000000000 @
b00000000000000000000000000111010 B
#1260000000
0!
00
#1270000000
1!
1'
0(
b1000000001011111 *
b00000000000000000000000000111010 +
b00001011 ,
1-
10
16
07
b1000000001011111 9
b00000000000000000000000000111010 :
b00001011 ;
1<
b00001100 =
0?
b00000000000000000000000000000001 @
b00000000000000000000000000111011 B
1C
0D
#1280000000
0!
00
#1290000000
1!
0-
10
0<
b00000000000000000000000000000010 @
b00000000000000000000000000111100 B
#1300000000
0!
0#
00
02
#1310000000
1!
10
0>
b00000000000000000000000000000011 @
b00000000000000000000000000111101 B
#1320000000
0!
00
#1330000000
1!
10
b00000000000000000000000000000100 @
b00000000000000000000000000111110 B
#1340000000
0!
00
#1350000000
1!
1#
10
12
1>
1?
b00000000000000000000000000000000 @
b00000000000000000000000000111111 B
#1360000000
0!
00
#1370000000
1!
b00000000000000000000000000111111 +
b00001100 ,
1-
10
b00000000000000000000000000111111 :
b00001100 ;
1<
b00001101 =
0?
b00000000000000000000000000000001 @
b00000000000000000000000001000000 B
#1380000000
0!
00
#1390000000
1!
0-
10
0<
b00000000000000000000000000000010 @
b00000000000000000000000001000001 B
#1400000000
0!
0#
00
02
#1410000000
1!
10
0>
b00000000000000000000000000000011 @
b00000000000000000000000001000010 B
#1420000000
0!
00
#1430000000
1!
10
b00000000000000000000000000000100 @
b00000000000000000000000001000011 B
#1440000000
0!
00
#1450000000
1!
1#
10
12
1>
1?
b00000000000000000000000000000000 @
b00000000000000000000000001000100 B
#1460000000
0!
00
#1470000000
1!
b00000000000000000000000001000100 +
b00001101 ,
1-
10
b00000000000000000000000001000100 :
b00001101 ;
1<
b00001110 =
0?
b00000000000000000000000000000001 @
b00000000000000000000000001000101 B
#1480000000
0!
00
#1490000000
1!
0-
10
0<
b00000000000000000000000000000010 @
b00000000000000000000000001000110 B
#1500000000
0!
0#
00
02
#1510000000
1!
10
0>
b00000000000000000000000000000011 @
b00000000000000000000000001000111 B
#1520000000
0!
00
#1530000000
1!
10
b00000000000000000000000000000100 @
b00000000000000000000000001001000 B
#1540000000
0!
00
#1550000000
1!
1#
10
12
1>
1?
b00000000000000000000000000000000 @
b00000000000000000000000001001001 B
#1560000000
0!
00
#1570000000
1!
b00000000000000000000000001001001 +
b00001110 ,
1-
10
b00000000000000000000000001001001 :
b00001110 ;
1<
b00001111 =
0?
b00000000000000000000000000000001 @
b00000000000000000000000001001010 B
#1580000000
0!
00
#1590000000
1!
0-
10
0<
b00000000000000000000000000000010 @
b00000000000000000000000001001011 B
#1600000000
0!
0#
0$
1%
00
02
03
14
#1610000000
1!
10
0>
b00000000000000000000000000000011 @
b00000000000000000000000001001100 B
#1620000000
0!
00
#1630000000
1!
10
b00000000000000000000000000000100 @
b00000000000000000000000001001101 B
#1640000000
0!
00
#1650000000
1!
1#
10
12
1>
1?
b00000000000000000000000000000000 @
b00000000000000000000000001001110 B
#1660000000
0!
00
#1670000000
1!
0'
1(
b0100000001011111 *
b00000000000000000000000001001110 +
b00001111 ,
1-
10
06
17
b0100000001011111 9
b00000000000000000000000001001110 :
b00001111 ;
1<
b00010000 =
0?
b00000000000000000000000000000001 @
b00000000000000000000000001001111 B
0C
1D
#1680000000
0!
00
#1690000000
1!
0-
10
0<
b00000000000000000000000000000010 @
b00000000000000000000000001010000 B
#1700000000
0!
0#
00
02
#1710000000
1!
10
0>
b00000000000000000000000000000011 @
b00000000000000000000000001010001 B
#1720000000
0!
00
#1730000000
1!
10
b00000000000000000000000000000100 @
b00000000000000000000000001010010 B
#1740000000
0!
00
#1750000000
1!
1#
10
12
1>
1?
b00000000000000000000000000000000 @
b00000000000000000000000001010011 B
#1760000000
0!
00
#1770000000
1!
b00000000000000000000000001010011 +
b00010000 ,
1-
10
b00000000000000000000000001010011 :
b00010000 ;
1<
b00010001 =
0?
b00000000000000000000000000000001 @
b00000000000000000000000001010100 B
#1780000000
0!
00
#1790000000
1!
0-
10
0<
b00000000000000000000000000000010 @
b00000000000000000000000001010101 B
#1800000000
0!
0#
1$
0%
00
02
13
04
#1810000000
1!
10
0>
b00000000000000000000000000000011 @
b00000000000000000000000001010110 B
#1820000000
0!
00
#1830000000
1!
10
b00000000000000000000000000000100 @
b00000000000000000000000001010111 B
#1840000000
0!
00
#1850000000
1!
1#
10
12
1>
1?
b00000000000000000000000000000000 @
b00000000000000000000000001011000 B
#1860000000
0!
00
#1870000000
1!
1'
0(
b1000000001011111 *
b00000000000000000000000001011000 +
b00010001 ,
1-
10
16
07
b1000000001011111 9
b00000000000000000000000001011000 :
b00010001 ;
1<
b00010010 =
0?
b00000000000000000000000000000001 @
b00000000000000000000000001011001 B
1C
0D
#1880000000
0!
00
#1890000000
1!
0-
10
0<
b00000000000000000000000000000010 @
b00000000000000000000000001011010 B
#1900000000
0!
0#
00
02
#1910000000
1!
10
0>
b00000000000000000000000000000011 @
b00000000000000000000000001011011 B
#1920000000
0!
00
#1930000000
1!
10
b00000000000000000000000000000100 @
b00000000000000000000000001011100 B
#1940000000
0!
00
#1950000000
1!
1#
10
12
1>
1?
b00000000000000000000000000000000 @
b00000000000000000000000001011101 B
#1960000000
0!
00
#1970000000
1!
b00000000000000000000000001011101 +
b00010010 ,
1-
10
b00000000000000000000000001011101 :
b00010010 ;
1<
b00010011 =
0?
b00000000000000000000000000000001 @
b00000000000000000000000001011110 B
#1980000000
0!
00
#1990000000
1!
0-
10
0<
b00000000000000000000000000000010 @
b00000000000000000000000001011111 B
#2000000000
0!
0#
0$
1%
00
02
03
14
#2010000000
1!
10
0>
b00000000000000000000000000000011 @
b00000000000000000000000001100000 B
#2020000000
0!
00
#2030000000
1!
10
b00000000000000000000000000000100 @
b00000000000000000000000001100001 B
#2040000000
0!
00
#2050000000
1!
1#
10
12
1>
1?
b00000000000000000000000000000000 @
b00000000000000000000000001100010 B
#2060000000
0!
00
#2070000000
1!
0'
1(
b0100000001011111 *
b00000000000000000000000001100010 +
b00010011 ,
1-
10
06
17
b0100000001011111 9
b00000000000000000000000001100010 :
b00010011 ;
1<
b00010100 =
0?
b00000000000000000000000000000001 @
b00000000000000000000000001100011 B
0C
1D
#2080000000
0!
00
#2090000000
1!
0-
10
0<
b00000000000000000000000000000010 @
b00000000000000000000000001100100 B
#2100000000
0!
0#
00
02
#2110000000
1!
10
0>
b00000000000000000000000000000011 @
b00000000000000000000000001100101 B
#2120000000
0!
00
#2130000000
1!
10
b00000000000000000000000000000100 @
b00000000000000000000000001100110 B
#2140000000
0!
00
#2150000000
1!
1#
10
12
1>
1?
b00000000000000000000000000000000 @
b00000000000000000000000001100111 B
#2160000000
0!
00
#2170000000
1!
b00000000000000000000000001100111 +
b00010100 ,
1-
10
b00000000000000000000000001100111 :
b00010100 ;
1<
b00010101 =
0?
b00000000000000000000000000000001 @
b00000000000000000000000001101000 B
#2180000000
0!
00
#2190000000
1!
0-
10
0<
b00000000000000000000000000000010 @
b00000000000000000000000001101001 B
#2200000000
0!
0#
1&
00
02
15
