sniffing/spi.vhd
library IEEE;
use IEEE.STD_LOGIC_1164.ALL;
use IEEE.NUMERIC_STD.ALL;

entity spi is
    Port (
        clk         : in  std_logic;
        reset       : in  std_logic;
        sclk        : in  std_logic;
        miso        : in  std_logic;
        mosi        : in  std_logic;
        cs          : in  std_logic;
        led_miso    : out std_logic;
        led_mosi    : out std_logic;
        led_cs      : out std_logic;
        led_sclk    : out std_logic;
        -- Circular buffer output
        buffer_data : out std_logic_vector(47 downto 0);  -- 48 bits: 16-bit data + 32-bit timestamp 
        buffer_addr : out std_logic_vector(7 downto 0);
        buffer_wr   : out std_logic
    );
end spi;

architecture Behavioral of spi is
    signal write_ptr : unsigned(7 downto 0) := (others => '0');
    
    -- Edge detection
    signal sclk_prev : std_logic := '0';
    signal sclk_rising : std_logic := '0';
    
    -- Frequency measurement
    signal sclk_counter : unsigned(31 downto 0) := (others => '0');
    signal sclk_period  : unsigned(31 downto 0) := (others => '0');
    
    -- Timestamp counter
    signal timestamp_counter : unsigned(31 downto 0) := (others => '0');
    
    -- Sampled SPI values
    signal miso_reg, mosi_reg, cs_reg : std_logic;
    
    -- Frequency calculation signals
    signal system_clk_freq : unsigned(31 downto 0) := to_unsigned(12000000, 32);  -- 200 MHz system clock
    signal calculated_freq : unsigned(31 downto 0) := (others => '0');
    signal freq_hz        : unsigned(12 downto 0) := (others => '0');
begin
    process(clk)
    begin
        if rising_edge(clk) then
            if reset = '1' then
                write_ptr         <= (others => '0');
                sclk_counter      <= (others => '0');
                sclk_period       <= (others => '0');
                timestamp_counter <= (others => '0');
                sclk_prev         <= '0';
                buffer_wr         <= '0';
                sclk_rising       <= '0';
                calculated_freq   <= (others => '0');
                freq_hz           <= (others => '0');
            else
                -- Timestamp increment
                timestamp_counter <= timestamp_counter + 1;
                
                -- Default state
                buffer_wr <= '0';
                sclk_rising <= '0';
                
                -- Edge detection
                if sclk = '1' and sclk_prev = '0' then
                    sclk_rising <= '1';
                    sclk_period  <= sclk_counter;
                    sclk_counter <= (others => '0');
                else
                    sclk_counter <= sclk_counter + 1;
                end if;
                sclk_prev <= sclk;
                
                -- Calculate actual frequency in Hz
                if sclk_period > 0 and sclk_period < system_clk_freq then
                    calculated_freq <= system_clk_freq / sclk_period;
                    -- Convert and store in 13-bit value
                    freq_hz <= resize(calculated_freq(31 downto 17), 13);
                else
                    calculated_freq <= (others => '0');
                    freq_hz <= (others => '0');
                end if;
                
                -- Update status LEDs
                led_sclk <= sclk;
                
                -- On rising edge of SCLK, sample signals and store to buffer
                if sclk_rising = '1' then
                    -- Sample and store SPI signals
                    miso_reg <= miso;
                    mosi_reg <= mosi;
                    cs_reg   <= cs;
                    
                    -- Update LEDs with current values
                    led_miso <= miso;
                    led_mosi <= mosi;
                    led_cs   <= cs;
                    
                    -- Provide data to output ports
                    buffer_data <= miso & mosi & cs & std_logic_vector(freq_hz) & std_logic_vector(timestamp_counter);
                    buffer_addr <= std_logic_vector(write_ptr);
                    buffer_wr   <= '1';
                    
                    -- Increment write pointer
                    write_ptr <= write_ptr + 1;
                end if;
            end if;
        end if;
    end process;
end Behavioral;

sniffing/spi_tb.vhd
library IEEE;
use IEEE.STD_LOGIC_1164.ALL;
use IEEE.NUMERIC_STD.ALL;

entity spi_tb is
-- Empty entity for testbench
end spi_tb;

architecture Behavioral of spi_tb is
    -- Component declaration for the Unit Under Test (UUT)
    component spi
        Port (
            clk         : in  std_logic;
            reset       : in  std_logic;
            sclk        : in  std_logic;
            miso        : in  std_logic;
            mosi        : in  std_logic;
            cs          : in  std_logic;
            led_miso    : out std_logic;
            led_mosi    : out std_logic;
            led_cs      : out std_logic;
            buffer_data : out std_logic_vector(47 downto 0);  -- Updated to 48 bits (timestamp + data)
            buffer_addr : out std_logic_vector(7 downto 0);
            buffer_wr   : out std_logic
        );
    end component;
    
    -- Testbench constants
    constant CLK_PERIOD : time := 5 ns;        -- 50 MHz system clock
    constant SCLK_PERIOD : time := 20 ns;      -- 5 MHz SPI clock (typical)
    
    -- Testbench signals
    signal clk_tb          : std_logic := '0';
    signal reset_tb        : std_logic := '0';
    signal sclk_tb         : std_logic := '0';
    signal miso_tb         : std_logic := '0';
    signal mosi_tb         : std_logic := '0';
    signal cs_tb           : std_logic := '1';  -- CS active low, initially inactive
    
    -- Output signals
    signal led_miso_tb     : std_logic;
    signal led_mosi_tb     : std_logic;
    signal led_cs_tb       : std_logic;
    signal buffer_data_tb  : std_logic_vector(47 downto 0);  -- Updated to 48 bits (timestamp + data)
    signal buffer_addr_tb  : std_logic_vector(7 downto 0);
    signal buffer_wr_tb    : std_logic;
    
    -- SPI test data
    type test_data_array is array (natural range <>) of std_logic_vector(7 downto 0);
    constant test_data : test_data_array := (
        X"A5",  -- 10100101
        X"3C",  -- 00111100
        X"F0"   -- 11110000
    );
    
    -- Function to convert std_logic_vector to hex string
    function to_hex_string(slv: std_logic_vector) return string is
        variable result: string(1 to slv'length/4);
        variable v: std_logic_vector(3 downto 0);
        variable c: character;
    begin
        for i in result'range loop
            v := slv((i*4)-1 downto (i-1)*4);
            case v is
                when "0000" => c := '0';
                when "0001" => c := '1';
                when "0010" => c := '2';
                when "0011" => c := '3';
                when "0100" => c := '4';
                when "0101" => c := '5';
                when "0110" => c := '6';
                when "0111" => c := '7';
                when "1000" => c := '8';
                when "1001" => c := '9';
                when "1010" => c := 'A';
                when "1011" => c := 'B';
                when "1100" => c := 'C';
                when "1101" => c := 'D';
                when "1110" => c := 'E';
                when "1111" => c := 'F';
                when others => c := 'X';
            end case;
            result(i) := c;
        end loop;
        return result;
    end function;
    
    -- Function to extract SPI signals and frequency from buffer data
    function decode_buffer_data(data: std_logic_vector(47 downto 0)) return string is
        variable timestamp : unsigned(31 downto 0) := unsigned(data(47 downto 16));
        variable miso_val : std_logic := data(15);
        variable mosi_val : std_logic := data(14);
        variable cs_val : std_logic := data(13);
        variable freq_100khz : integer := to_integer(unsigned(data(12 downto 0)));
        variable freq_khz : integer := freq_100khz * 100;
    begin
        return "MISO=" & std_logic'image(miso_val) & 
               ", MOSI=" & std_logic'image(mosi_val) & 
               ", CS=" & std_logic'image(cs_val) & 
               ", Freq=" & integer'image(freq_khz) & " kHz (" & 
               integer'image(freq_khz / 1000) & "." & 
               integer'image((freq_khz mod 1000) / 100) & " MHz)" &
               ", Timestamp=" & integer'image(to_integer(timestamp));
    end function;
    
    -- Additional variables for test cases with varying SPI clock frequencies
    signal sclk_divider : integer := 5;  -- Initially 5 MHz (50 MHz / 10)
    
    -- Simulation control
    signal sim_done : boolean := false;
    
begin
    -- Instantiate the Unit Under Test (UUT)
    uut: spi
    port map (
        clk => clk_tb,
        reset => reset_tb,
        sclk => sclk_tb,
        miso => miso_tb,
        mosi => mosi_tb,
        cs => cs_tb,
        led_miso => led_miso_tb,
        led_mosi => led_mosi_tb,
        led_cs => led_cs_tb,
        buffer_data => buffer_data_tb,
        buffer_addr => buffer_addr_tb,
        buffer_wr => buffer_wr_tb
    );
    
    -- Clock generation process for system clock
    clk_process: process
    begin
        while not sim_done loop
            clk_tb <= '0';
            wait for CLK_PERIOD/2;
            clk_tb <= '1';
            wait for CLK_PERIOD/2;
        end loop;
        wait;
    end process;
    
    -- Dynamic SPI Clock generation process
    -- Now with variable frequency for testing frequency detection
    spi_clk_process: process
        variable sclk_half_period : time;
    begin
        while not sim_done loop
            sclk_half_period := (CLK_PERIOD * sclk_divider) / 2;
            sclk_tb <= '0';
            wait for sclk_half_period;
            sclk_tb <= '1';
            wait for sclk_half_period;
        end loop;
        wait;
    end process;
    
    -- Stimulus process
    stim_proc: process
    begin
        -- Initial reset
        reset_tb <= '0';  -- Active low reset
        wait for 100 ns;
        reset_tb <= '1';  -- Release reset
        wait for 100 ns;
        
        -- Test Case 1: Send multiple bytes through SPI at 5 MHz
        report "Test Case 1: SPI Transfer at 5 MHz";
        sclk_divider <= 5;  -- 50 MHz / 5 = 10 MHz
        wait for 200 ns;    -- Wait for clock stabilization
        
        for byte_idx in test_data'range loop
            -- Start SPI transaction (CS active low)
            cs_tb <= '0';
            wait for SCLK_PERIOD;
            
            -- Send 8 bits MSB first
            for bit_idx in 7 downto 0 loop
                -- Set MOSI based on test data
                mosi_tb <= test_data(byte_idx)(bit_idx);
                
                -- Set MISO to inverse of MOSI for simple test pattern
                miso_tb <= not test_data(byte_idx)(bit_idx);
                
                -- Wait for a full SCLK cycle
                wait for SCLK_PERIOD;
            end loop;
            
            -- End transaction with CS high
            cs_tb <= '1';
            wait for SCLK_PERIOD * 2;
        end loop;
        
        -- Test Case 2: Check frequency detection at 1 MHz
        report "Test Case 2: SPI Transfer at 1 MHz";
        sclk_divider <= 25;  -- 50 MHz / 25 = 2 MHz
        wait for 1 us;      -- Wait for clock stabilization
        
        cs_tb <= '0';
        
        for i in 0 to 15 loop
            -- Alternate MOSI for a simple pattern
            mosi_tb <= not mosi_tb;
            
            -- MISO with a different pattern
            if i mod 2 = 0 then
                miso_tb <= not miso_tb;
            end if;
            
            wait for SCLK_PERIOD * 5;  -- Adjusted for slower clock
        end loop;
        
        cs_tb <= '1';
        wait for SCLK_PERIOD * 5;
        
        -- Test Case 3: Check frequency detection at 10 MHz
        report "Test Case 3: SPI Transfer at 10 MHz";
        sclk_divider <= 2;  -- 50 MHz / 2 = 25 MHz
        wait for 1 us;      -- Wait for clock stabilization
        
        cs_tb <= '0';
        for i in 0 to 7 loop
            mosi_tb <= not mosi_tb;
            miso_tb <= not miso_tb;
            wait for SCLK_PERIOD / 2;  -- Adjusted for faster clock
        end loop;
        cs_tb <= '1';
        wait for SCLK_PERIOD;
        
        -- Test Case 4: Reset during transfer
        report "Test Case 4: Reset during transfer";
        sclk_divider <= 5;  -- Back to original speed
        wait for 1 us;
        
        cs_tb <= '0';
        mosi_tb <= '1';
        miso_tb <= '0';
        wait for SCLK_PERIOD * 3;
        
        -- Apply reset in the middle of transaction
        reset_tb <= '0';
        wait for SCLK_PERIOD * 2;
        reset_tb <= '1';
        wait for SCLK_PERIOD * 2;
        
        -- Continue with transfer
        for i in 0 to 7 loop
            mosi_tb <= not mosi_tb;
            wait for SCLK_PERIOD;
        end loop;
        
        cs_tb <= '1';
        wait for SCLK_PERIOD * 4;
        
        -- End simulation
        sim_done <= true;
        wait for 100 ns;
        
        report "Simulation completed successfully";
        wait;
    end process;
    
    -- Monitor process to check output signals
    monitor_proc: process
    begin
        wait until rising_edge(clk_tb);
        
        if buffer_wr_tb = '1' then
            report "Buffer Write: Address = " & 
                   integer'image(to_integer(unsigned(buffer_addr_tb))) & 
                   ", Data = 0x" & to_hex_string(buffer_data_tb) & 
                   ", " & decode_buffer_data(buffer_data_tb);
        end if;
        
        if sim_done then
            wait;
        end if;
    end process;
    
end Behavioral;

sniffing/spi_simulation.vcd
$date
  Tue Apr 29 10:53:37 2025
$end
$version
  GHDL v0
$end
$timescale
  1 fs
$end
$scope module standard $end
$upscope $end
$scope module std_logic_1164 $end
$upscope $end
$scope module numeric_std $end
$upscope $end
$scope module spi_tb $end
$var reg 1 ! clk_tb $end
$var reg 1 " reset_tb $end
$var reg 1 # sclk_tb $end
$var reg 1 $ miso_tb $end
$var reg 1 % mosi_tb $end
$var reg 1 & cs_tb $end
$var reg 1 ' led_miso_tb $end
$var reg 1 ( led_mosi_tb $end
$var reg 1 ) led_cs_tb $end
$var reg 48 * buffer_data_tb[47:0] $end
$var reg 8 + buffer_addr_tb[7:0] $end
$var reg 1 , buffer_wr_tb $end
$var integer 32 - sclk_divider $end
$var reg 1 . sim_done $end
$scope module uut $end
$var reg 1 / clk $end
$var reg 1 0 reset $end
$var reg 1 1 sclk $end
$var reg 1 2 miso $end
$var reg 1 3 mosi $end
$var reg 1 4 cs $end
$var reg 1 5 led_miso $end
$var reg 1 6 led_mosi $end
$var reg 1 7 led_cs $end
$var reg 1 8 led_sclk $end
$var reg 48 9 buffer_data[47:0] $end
$var reg 8 : buffer_addr[7:0] $end
$var reg 1 ; buffer_wr $end
$comment circ_buffer is not handled $end
$var reg 8 < write_ptr[7:0] $end
$var reg 1 = sclk_prev $end
$var reg 1 > sclk_rising $end
$var reg 32 ? sclk_counter[31:0] $end
$var reg 32 @ sclk_period[31:0] $end
$var reg 32 A timestamp_counter[31:0] $end
$var reg 1 B miso_reg $end
$var reg 1 C mosi_reg $end
$var reg 1 D cs_reg $end
$var reg 32 E system_clk_freq[31:0] $end
$var reg 32 F calculated_freq[31:0] $end
$var reg 13 G freq_hz[12:0] $end
$upscope $end
$upscope $end
$enddefinitions $end
#0
0!
0"
0#
0$
0%
1&
U'
U(
U)
bUUUUUUUUUUUUUUUUUUUUUUUUUUUUUUUUUUUUUUUUUUUUUUUU *
bUUUUUUUU +
U,
b101 -
0.
0/
00
01
02
03
14
U5
U6
U7
U8
bUUUUUUUUUUUUUUUUUUUUUUUUUUUUUUUUUUUUUUUUUUUUUUUU 9
bUUUUUUUU :
U;
b00000000 <
0=
0>
b00000000000000000000000000000000 ?
b00000000000000000000000000000000 @
b00000000000000000000000000000000 A
UB
UC
UD
b00001011111010111100001000000000 E
b00000000000000000000000000000000 F
b0000000000000 G
#2500000
1!
0,
1/
08
0;
b00000000000000000000000000000001 ?
b00000000000000000000000000000001 A
#5000000
0!
0/
#7500000
1!
1/
b00000000000000000000000000000010 ?
b00000000000000000000000000000010 A
#10000000
0!
0/
#12500000
1!
1#
1/
11
18
1=
1>
b00000000000000000000000000000000 ?
b00000000000000000000000000000010 @
b00000000000000000000000000000011 A
#15000000
0!
0/
#17500000
1!
0'
0(
1)
b000000000000000000000000000000110010000000000000 *
b00000000 +
1,
1/
05
06
17
b000000000000000000000000000000110010000000000000 9
b00000000 :
1;
b00000001 <
0>
b00000000000000000000000000000001 ?
b00000000000000000000000000000100 A
0B
0C
1D
b00000101111101011110000100000000 F
#20000000
0!
0/
#22500000
1!
0,
1/
0;
b00000000000000000000000000000010 ?
b00000000000000000000000000000101 A
b0001011111010 G
#25000000
0!
0#
0/
01
#27500000
1!
1/
08
0=
b00000000000000000000000000000011 ?
b00000000000000000000000000000110 A
#30000000
0!
0/
#32500000
1!
1/
b00000000000000000000000000000100 ?
b00000000000000000000000000000111 A
#35000000
0!
0/
#37500000
1!
1#
1/
11
18
1=
1>
b00000000000000000000000000000000 ?
b00000000000000000000000000000100 @
b00000000000000000000000000001000 A
#40000000
0!
0/
#42500000
1!
b000000000000000000000000000010000010001011111010 *
b00000001 +
1,
1/
b000000000000000000000000000010000010001011111010 9
b00000001 :
1;
b00000010 <
0>
b00000000000000000000000000000001 ?
b00000000000000000000000000001001 A
b00000010111110101111000010000000 F
#45000000
0!
0/
#47500000
1!
0,
1/
0;
b00000000000000000000000000000010 ?
b00000000000000000000000000001010 A
b0000101111101 G
#50000000
0!
0#
0/
01
#52500000
1!
1/
08
0=
b00000000000000000000000000000011 ?
b00000000000000000000000000001011 A
#55000000
0!
0/
#57500000
1!
1/
b00000000000000000000000000000100 ?
b00000000000000000000000000001100 A
#60000000
0!
0/
#62500000
1!
1#
1/
11
18
1=
1>
b00000000000000000000000000000000 ?
b00000000000000000000000000001101 A
#65000000
0!
0/
#67500000
1!
b000000000000000000000000000011010010000101111101 *
b00000010 +
1,
1/
b000000000000000000000000000011010010000101111101 9
b00000010 :
1;
b00000011 <
0>
b00000000000000000000000000000001 ?
b00000000000000000000000000001110 A
#70000000
0!
0/
#72500000
1!
0,
1/
0;
b00000000000000000000000000000010 ?
b00000000000000000000000000001111 A
#75000000
0!
0#
0/
01
#77500000
1!
1/
08
0=
b00000000000000000000000000000011 ?
b00000000000000000000000000010000 A
#80000000
0!
0/
#82500000
1!
1/
b00000000000000000000000000000100 ?
b00000000000000000000000000010001 A
#85000000
0!
0/
#87500000
1!
1#
1/
11
18
1=
1>
b00000000000000000000000000000000 ?
b00000000000000000000000000010010 A
#90000000
0!
0/
#92500000
1!
b000000000000000000000000000100100010000101111101 *
b00000011 +
1,
1/
b000000000000000000000000000100100010000101111101 9
b00000011 :
1;
b00000100 <
0>
b00000000000000000000000000000001 ?
b00000000000000000000000000010011 A
#95000000
0!
0/
#97500000
1!
0,
1/
0;
b00000000000000000000000000000010 ?
b00000000000000000000000000010100 A
#100000000
0!
1"
0#
0/
10
01
#102500000
1!
1/
b00000000 <
0=
b00000000000000000000000000000000 ?
b00000000000000000000000000000000 @
b00000000000000000000000000000000 A
b00000000000000000000000000000000 F
b0000000000000 G
