sniffing/spi.vhd
library IEEE;
use IEEE.STD_LOGIC_1164.ALL;
use IEEE.NUMERIC_STD.ALL;

entity spi is
    Port (
        clk         : in  std_logic;              
        reset       : in  std_logic;
        sclk        : in  std_logic;              
        miso        : in  std_logic;
        mosi        : in  std_logic;
        cs          : in  std_logic;
        led_miso    : out std_logic;
        led_mosi    : out std_logic;
        led_cs      : out std_logic;
        -- Circular buffer output
        buffer_data : out std_logic_vector(47 downto 0);  -- 16 bits for data (miso, mosi, cs, (13) sclk freq)
        buffer_addr : out std_logic_vector(7 downto 0);
        buffer_wr   : out std_logic
    );
end spi;

architecture Behavioral of spi is
    -- Buffer entry: 16-bit data + 32-bit timestamp
    type spi_sample is record
        data      : std_logic_vector(15 downto 0);  
        timestamp : std_logic_vector(31 downto 0);
    end record;
    -- Circular buffer type
    type buffer_type is array (0 to 255) of spi_sample;
    signal circ_buffer : buffer_type;
    signal write_ptr : unsigned(7 downto 0) := (others => '0');
    
    -- Edge detection
    signal sclk_prev : std_logic := '0';
    signal sclk_rising : std_logic := '0';
    
    -- Frequency measurement
    signal sclk_counter : unsigned(31 downto 0) := (others => '0');
    signal sclk_period  : unsigned(31 downto 0) := (others => '0');
    
    -- Timestamp counter
    signal timestamp_counter : unsigned(31 downto 0) := (others => '0');
    
    -- Sampled SPI values
    signal miso_reg, mosi_reg, cs_reg : std_logic;
    
    -- Frequency calculation signals
    signal system_clk_freq : unsigned(31 downto 0) := to_unsigned(200000000, 32);  -- Assuming 50 MHz system clock
    signal calculated_freq : unsigned(31 downto 0) := (others => '0');           -- Frequency in Hz
    signal freq_hz        : unsigned(12 downto 0) := (others => '0');           -- Frequency in Hz for buffer
begin
    process(clk)
    begin
        if rising_edge(clk) then
            if reset = '0' then
                write_ptr         <= (others => '0');
                sclk_counter      <= (others => '0');
                sclk_period       <= (others => '0');
                timestamp_counter <= (others => '0');
                sclk_prev         <= '0';
                buffer_wr         <= '0';
                sclk_rising       <= '0';
                calculated_freq   <= (others => '0');
                freq_hz           <= (others => '0');
            else
                -- Timestamp increment
                timestamp_counter <= timestamp_counter + 1;
                
                -- Default state
                buffer_wr <= '0';
                sclk_rising <= '0';
                
                if sclk = '1' and sclk_prev = '0' then
                    sclk_rising <= '1';
                    sclk_period  <= sclk_counter;
                    sclk_counter <= (others => '0');
                else
                    sclk_counter <= sclk_counter + 1;
                end if;
                sclk_prev <= sclk;
                
                -- Calculate actual frequency in Hz
                -- Frequency = System clock frequency / Period
                if sclk_period > 0 and sclk_period < system_clk_freq then
                    calculated_freq <= system_clk_freq / sclk_period;
                    -- Convert to 100 kHz units (divide by 100,000)
                    -- Integer division by 100,000 is equivalent to shifting right by 16.61 bits
                    -- We'll use a 17-bit shift for simplicity and efficiency (divide by 131,072)
                    freq_hz <= resize(calculated_freq(31 downto 17), 13);
                else
                    calculated_freq <= (others => '0');
                    freq_hz <= (others => '0');
                end if;
                
                if sclk_rising = '1' then
                    miso_reg <= miso;
                    mosi_reg <= mosi;
                    cs_reg   <= cs;
                    
                    -- Update LEDs (could be removed in future)
						  led_miso <= miso;
                    led_mosi <= mosi;
                    led_cs   <= cs;
                    
                    circ_buffer(to_integer(write_ptr)).data      <= miso & mosi & cs & std_logic_vector(freq_hz);
                    circ_buffer(to_integer(write_ptr)).timestamp <= std_logic_vector(timestamp_counter);
                    
                    buffer_data <= std_logic_vector(timestamp_counter) & miso & mosi & cs & std_logic_vector(freq_hz);
                    buffer_addr <= std_logic_vector(write_ptr);
                    buffer_wr   <= '1';
                    
                    write_ptr <= write_ptr + 1;
                end if;
            end if;
        end if;
    end process;
end Behavioral;

sniffing/spi_tb.vhd
library IEEE;
use IEEE.STD_LOGIC_1164.ALL;
use IEEE.NUMERIC_STD.ALL;

entity spi_tb is
-- Empty entity for testbench
end spi_tb;

architecture Behavioral of spi_tb is
    -- Component declaration for the Unit Under Test (UUT)
    component spi
        Port (
            clk         : in  std_logic;
            reset       : in  std_logic;
            sclk        : in  std_logic;
            miso        : in  std_logic;
            mosi        : in  std_logic;
            cs          : in  std_logic;
            led_miso    : out std_logic;
            led_mosi    : out std_logic;
            led_cs      : out std_logic;
            buffer_data : out std_logic_vector(47 downto 0);  -- Updated to 48 bits (timestamp + data)
            buffer_addr : out std_logic_vector(7 downto 0);
            buffer_wr   : out std_logic
        );
    end component;
    
    -- Testbench constants
    constant CLK_PERIOD : time := 5 ns;        -- 50 MHz system clock
    constant SCLK_PERIOD : time := 20 ns;      -- 5 MHz SPI clock (typical)
    
    -- Testbench signals
    signal clk_tb          : std_logic := '0';
    signal reset_tb        : std_logic := '0';
    signal sclk_tb         : std_logic := '0';
    signal miso_tb         : std_logic := '0';
    signal mosi_tb         : std_logic := '0';
    signal cs_tb           : std_logic := '1';  -- CS active low, initially inactive
    
    -- Output signals
    signal led_miso_tb     : std_logic;
    signal led_mosi_tb     : std_logic;
    signal led_cs_tb       : std_logic;
    signal buffer_data_tb  : std_logic_vector(47 downto 0);  -- Updated to 48 bits (timestamp + data)
    signal buffer_addr_tb  : std_logic_vector(7 downto 0);
    signal buffer_wr_tb    : std_logic;
    
    -- SPI test data
    type test_data_array is array (natural range <>) of std_logic_vector(7 downto 0);
    constant test_data : test_data_array := (
        X"A5",  -- 10100101
        X"3C",  -- 00111100
        X"F0"   -- 11110000
    );
    
    -- Function to convert std_logic_vector to hex string
    function to_hex_string(slv: std_logic_vector) return string is
        variable result: string(1 to slv'length/4);
        variable v: std_logic_vector(3 downto 0);
        variable c: character;
    begin
        for i in result'range loop
            v := slv((i*4)-1 downto (i-1)*4);
            case v is
                when "0000" => c := '0';
                when "0001" => c := '1';
                when "0010" => c := '2';
                when "0011" => c := '3';
                when "0100" => c := '4';
                when "0101" => c := '5';
                when "0110" => c := '6';
                when "0111" => c := '7';
                when "1000" => c := '8';
                when "1001" => c := '9';
                when "1010" => c := 'A';
                when "1011" => c := 'B';
                when "1100" => c := 'C';
                when "1101" => c := 'D';
                when "1110" => c := 'E';
                when "1111" => c := 'F';
                when others => c := 'X';
            end case;
            result(i) := c;
        end loop;
        return result;
    end function;
    
    -- Function to extract SPI signals and frequency from buffer data
    function decode_buffer_data(data: std_logic_vector(47 downto 0)) return string is
        variable timestamp : unsigned(31 downto 0) := unsigned(data(47 downto 16));
        variable miso_val : std_logic := data(15);
        variable mosi_val : std_logic := data(14);
        variable cs_val : std_logic := data(13);
        variable freq_100khz : integer := to_integer(unsigned(data(12 downto 0)));
        variable freq_khz : integer := freq_100khz * 100;
    begin
        return "MISO=" & std_logic'image(miso_val) & 
               ", MOSI=" & std_logic'image(mosi_val) & 
               ", CS=" & std_logic'image(cs_val) & 
               ", Freq=" & integer'image(freq_khz) & " kHz (" & 
               integer'image(freq_khz / 1000) & "." & 
               integer'image((freq_khz mod 1000) / 100) & " MHz)" &
               ", Timestamp=" & integer'image(to_integer(timestamp));
    end function;
    
    -- Additional variables for test cases with varying SPI clock frequencies
    signal sclk_divider : integer := 5;  -- Initially 5 MHz (50 MHz / 10)
    
    -- Simulation control
    signal sim_done : boolean := false;
    
begin
    -- Instantiate the Unit Under Test (UUT)
    uut: spi
    port map (
        clk => clk_tb,
        reset => reset_tb,
        sclk => sclk_tb,
        miso => miso_tb,
        mosi => mosi_tb,
        cs => cs_tb,
        led_miso => led_miso_tb,
        led_mosi => led_mosi_tb,
        led_cs => led_cs_tb,
        buffer_data => buffer_data_tb,
        buffer_addr => buffer_addr_tb,
        buffer_wr => buffer_wr_tb
    );
    
    -- Clock generation process for system clock
    clk_process: process
    begin
        while not sim_done loop
            clk_tb <= '0';
            wait for CLK_PERIOD/2;
            clk_tb <= '1';
            wait for CLK_PERIOD/2;
        end loop;
        wait;
    end process;
    
    -- Dynamic SPI Clock generation process
    -- Now with variable frequency for testing frequency detection
    spi_clk_process: process
        variable sclk_half_period : time;
    begin
        while not sim_done loop
            sclk_half_period := (CLK_PERIOD * sclk_divider) / 2;
            sclk_tb <= '0';
            wait for sclk_half_period;
            sclk_tb <= '1';
            wait for sclk_half_period;
        end loop;
        wait;
    end process;
    
    -- Stimulus process
    stim_proc: process
    begin
        -- Initial reset
        reset_tb <= '0';  -- Active low reset
        wait for 100 ns;
        reset_tb <= '1';  -- Release reset
        wait for 100 ns;
        
        -- Test Case 1: Send multiple bytes through SPI at 5 MHz
        report "Test Case 1: SPI Transfer at 5 MHz";
        sclk_divider <= 5;  -- 50 MHz / 5 = 10 MHz
        wait for 200 ns;    -- Wait for clock stabilization
        
        for byte_idx in test_data'range loop
            -- Start SPI transaction (CS active low)
            cs_tb <= '0';
            wait for SCLK_PERIOD;
            
            -- Send 8 bits MSB first
            for bit_idx in 7 downto 0 loop
                -- Set MOSI based on test data
                mosi_tb <= test_data(byte_idx)(bit_idx);
                
                -- Set MISO to inverse of MOSI for simple test pattern
                miso_tb <= not test_data(byte_idx)(bit_idx);
                
                -- Wait for a full SCLK cycle
                wait for SCLK_PERIOD;
            end loop;
            
            -- End transaction with CS high
            cs_tb <= '1';
            wait for SCLK_PERIOD * 2;
        end loop;
        
        -- Test Case 2: Check frequency detection at 1 MHz
        report "Test Case 2: SPI Transfer at 1 MHz";
        sclk_divider <= 25;  -- 50 MHz / 25 = 2 MHz
        wait for 1 us;      -- Wait for clock stabilization
        
        cs_tb <= '0';
        
        for i in 0 to 15 loop
            -- Alternate MOSI for a simple pattern
            mosi_tb <= not mosi_tb;
            
            -- MISO with a different pattern
            if i mod 2 = 0 then
                miso_tb <= not miso_tb;
            end if;
            
            wait for SCLK_PERIOD * 5;  -- Adjusted for slower clock
        end loop;
        
        cs_tb <= '1';
        wait for SCLK_PERIOD * 5;
        
        -- Test Case 3: Check frequency detection at 10 MHz
        report "Test Case 3: SPI Transfer at 10 MHz";
        sclk_divider <= 2;  -- 50 MHz / 2 = 25 MHz
        wait for 1 us;      -- Wait for clock stabilization
        
        cs_tb <= '0';
        for i in 0 to 7 loop
            mosi_tb <= not mosi_tb;
            miso_tb <= not miso_tb;
            wait for SCLK_PERIOD / 2;  -- Adjusted for faster clock
        end loop;
        cs_tb <= '1';
        wait for SCLK_PERIOD;
        
        -- Test Case 4: Reset during transfer
        report "Test Case 4: Reset during transfer";
        sclk_divider <= 5;  -- Back to original speed
        wait for 1 us;
        
        cs_tb <= '0';
        mosi_tb <= '1';
        miso_tb <= '0';
        wait for SCLK_PERIOD * 3;
        
        -- Apply reset in the middle of transaction
        reset_tb <= '0';
        wait for SCLK_PERIOD * 2;
        reset_tb <= '1';
        wait for SCLK_PERIOD * 2;
        
        -- Continue with transfer
        for i in 0 to 7 loop
            mosi_tb <= not mosi_tb;
            wait for SCLK_PERIOD;
        end loop;
        
        cs_tb <= '1';
        wait for SCLK_PERIOD * 4;
        
        -- End simulation
        sim_done <= true;
        wait for 100 ns;
        
        report "Simulation completed successfully";
        wait;
    end process;
    
    -- Monitor process to check output signals
    monitor_proc: process
    begin
        wait until rising_edge(clk_tb);
        
        if buffer_wr_tb = '1' then
            report "Buffer Write: Address = " & 
                   integer'image(to_integer(unsigned(buffer_addr_tb))) & 
                   ", Data = 0x" & to_hex_string(buffer_data_tb) & 
                   ", " & decode_buffer_data(buffer_data_tb);
        end if;
        
        if sim_done then
            wait;
        end if;
    end process;
    
end Behavioral;

sniffing/spi_simulation.vcd
$date
  Fri Apr 18 09:41:11 2025
$end
$version
  GHDL v0
$end
$timescale
  1 fs
$end
$scope module standard $end
$upscope $end
$scope module std_logic_1164 $end
$upscope $end
$scope module numeric_std $end
$upscope $end
$scope module spi_tb $end
$var reg 1 ! clk_tb $end
$var reg 1 " reset_tb $end
$var reg 1 # sclk_tb $end
$var reg 1 $ miso_tb $end
$var reg 1 % mosi_tb $end
$var reg 1 & cs_tb $end
$var reg 1 ' led_miso_tb $end
$var reg 1 ( led_mosi_tb $end
$var reg 1 ) led_cs_tb $end
$var reg 48 * buffer_data_tb[47:0] $end
$var reg 8 + buffer_addr_tb[7:0] $end
$var reg 1 , buffer_wr_tb $end
$var integer 32 - sclk_divider $end
$var reg 1 . sim_done $end
$scope module uut $end
$var reg 1 / clk $end
$var reg 1 0 reset $end
$var reg 1 1 sclk $end
$var reg 1 2 miso $end
$var reg 1 3 mosi $end
$var reg 1 4 cs $end
$var reg 1 5 led_miso $end
$var reg 1 6 led_mosi $end
$var reg 1 7 led_cs $end
$var reg 48 8 buffer_data[47:0] $end
$var reg 8 9 buffer_addr[7:0] $end
$var reg 1 : buffer_wr $end
$comment circ_buffer is not handled $end
$var reg 8 ; write_ptr[7:0] $end
$var reg 1 < sclk_prev $end
$var reg 1 = sclk_rising $end
$var reg 32 > sclk_counter[31:0] $end
$var reg 32 ? sclk_period[31:0] $end
$var reg 32 @ timestamp_counter[31:0] $end
$var reg 1 A miso_reg $end
$var reg 1 B mosi_reg $end
$var reg 1 C cs_reg $end
$var reg 32 D system_clk_freq[31:0] $end
$var reg 32 E calculated_freq[31:0] $end
$var reg 13 F freq_hz[12:0] $end
$upscope $end
$upscope $end
$enddefinitions $end
#0
0!
0"
0#
0$
0%
1&
U'
U(
U)
bUUUUUUUUUUUUUUUUUUUUUUUUUUUUUUUUUUUUUUUUUUUUUUUU *
bUUUUUUUU +
U,
b101 -
0.
0/
00
01
02
03
14
U5
U6
U7
bUUUUUUUUUUUUUUUUUUUUUUUUUUUUUUUUUUUUUUUUUUUUUUUU 8
bUUUUUUUU 9
U:
b00000000 ;
0<
0=
b00000000000000000000000000000000 >
b00000000000000000000000000000000 ?
b00000000000000000000000000000000 @
UA
UB
UC
b00001011111010111100001000000000 D
b00000000000000000000000000000000 E
b0000000000000 F
#2500000
1!
0,
1/
0:
#5000000
0!
0/
#7500000
1!
1/
#10000000
0!
0/
#12500000
1!
1#
1/
11
#15000000
0!
0/
#17500000
1!
1/
#20000000
0!
0/
#22500000
1!
1/
#25000000
0!
0#
0/
01
#27500000
1!
1/
#30000000
0!
0/
#32500000
1!
1/
#35000000
0!
0/
#37500000
1!
1#
1/
11
#40000000
0!
0/
#42500000
1!
1/
#45000000
0!
0/
#47500000
1!
1/
#50000000
0!
0#
0/
01
#52500000
1!
1/
#55000000
0!
0/
#57500000
1!
1/
#60000000
0!
0/
#62500000
1!
1#
1/
11
#65000000
0!
0/
#67500000
1!
1/
#70000000
0!
0/
#72500000
1!
1/
#75000000
0!
0#
0/
01
#77500000
1!
1/
#80000000
0!
0/
#82500000
1!
1/
#85000000
0!
0/
#87500000
1!
1#
1/
11
#90000000
0!
0/
#92500000
1!
1/
#95000000
0!
0/
#97500000
1!
1/
#100000000
0!
1"
0#
0/
10
01
#102500000
1!
1/
b00000000000000000000000000000001 >
b00000000000000000000000000000001 @
#105000000
0!
0/
#107500000
1!
1/
b00000000000000000000000000000010 >
b00000000000000000000000000000010 @
#110000000
0!
0/
#112500000
1!
1#
1/
11
1<
1=
b00000000000000000000000000000000 >
b00000000000000000000000000000010 ?
b00000000000000000000000000000011 @
#115000000
0!
0/
#117500000
1!
0'
0(
1)
b000000000000000000000000000000110010000000000000 *
b00000000 +
1,
1/
05
06
17
b000000000000000000000000000000110010000000000000 8
b00000000 9
1:
b00000001 ;
0=
b00000000000000000000000000000001 >
b00000000000000000000000000000100 @
0A
0B
1C
b00000101111101011110000100000000 E
#120000000
0!
0/
#122500000
1!
0,
1/
0:
b00000000000000000000000000000010 >
b00000000000000000000000000000101 @
b0001011111010 F
#125000000
0!
0#
0/
01
#127500000
1!
1/
0<
b00000000000000000000000000000011 >
b00000000000000000000000000000110 @
#130000000
0!
0/
#132500000
1!
1/
b00000000000000000000000000000100 >
b00000000000000000000000000000111 @
#135000000
0!
0/
#137500000
1!
1#
1/
11
1<
1=
b00000000000000000000000000000000 >
b00000000000000000000000000000100 ?
b00000000000000000000000000001000 @
#140000000
0!
0/
#142500000
1!
b000000000000000000000000000010000010001011111010 *
b00000001 +
1,
1/
b000000000000000000000000000010000010001011111010 8
b00000001 9
1:
b00000010 ;
0=
b00000000000000000000000000000001 >
b00000000000000000000000000001001 @
b00000010111110101111000010000000 E
#145000000
0!
0/
#147500000
1!
0,
1/
0:
b00000000000000000000000000000010 >
b00000000000000000000000000001010 @
b0000101111101 F
#150000000
0!
0#
0/
01
#152500000
1!
1/
0<
b00000000000000000000000000000011 >
b00000000000000000000000000001011 @
#155000000
0!
0/
#157500000
1!
1/
b00000000000000000000000000000100 >
b00000000000000000000000000001100 @
#160000000
0!
0/
#162500000
1!
1#
1/
11
1<
1=
b00000000000000000000000000000000 >
b00000000000000000000000000001101 @
#165000000
0!
0/
#167500000
1!
b000000000000000000000000000011010010000101111101 *
b00000010 +
1,
1/
b000000000000000000000000000011010010000101111101 8
b00000010 9
1:
b00000011 ;
0=
b00000000000000000000000000000001 >
b00000000000000000000000000001110 @
#170000000
0!
0/
#172500000
1!
0,
1/
0:
b00000000000000000000000000000010 >
b00000000000000000000000000001111 @
#175000000
0!
0#
0/
01
#177500000
1!
1/
0<
b00000000000000000000000000000011 >
b00000000000000000000000000010000 @
#180000000
0!
0/
#182500000
1!
1/
b00000000000000000000000000000100 >
b00000000000000000000000000010001 @
#185000000
0!
0/
#187500000
1!
1#
1/
11
1<
1=
b00000000000000000000000000000000 >
b00000000000000000000000000010010 @
#190000000
0!
0/
#192500000
1!
b000000000000000000000000000100100010000101111101 *
b00000011 +
1,
1/
b000000000000000000000000000100100010000101111101 8
b00000011 9
1:
b00000100 ;
0=
b00000000000000000000000000000001 >
b00000000000000000000000000010011 @
#195000000
0!
0/
#197500000
1!
0,
1/
0:
b00000000000000000000000000000010 >
b00000000000000000000000000010100 @
#200000000
0!
0#
0/
01
#202500000
1!
1/
0<
b00000000000000000000000000000011 >
b00000000000000000000000000010101 @
#205000000
0!
0/
#207500000
1!
1/
b00000000000000000000000000000100 >
b00000000000000000000000000010110 @
#210000000
0!
0/
#212500000
1!
1#
1/
11
1<
1=
b00000000000000000000000000000000 >
b00000000000000000000000000010111 @
#215000000
0!
0/
#217500000
1!
b000000000000000000000000000101110010000101111101 *
b00000100 +
1,
1/
b000000000000000000000000000101110010000101111101 8
b00000100 9
1:
b00000101 ;
0=
b00000000000000000000000000000001 >
b00000000000000000000000000011000 @
#220000000
0!
0/
#222500000
1!
0,
1/
0:
b00000000000000000000000000000010 >
b00000000000000000000000000011001 @
#225000000
0!
0#
0/
01
#227500000
1!
1/
0<
b00000000000000000000000000000011 >
b00000000000000000000000000011010 @
#230000000
0!
0/
#232500000
1!
1/
b00000000000000000000000000000100 >
b00000000000000000000000000011011 @
#235000000
0!
0/
#237500000
1!
1#
1/
11
1<
1=
b00000000000000000000000000000000 >
b00000000000000000000000000011100 @
#240000000
0!
0/
#242500000
1!
b000000000000000000000000000111000010000101111101 *
b00000101 +
1,
1/
b000000000000000000000000000111000010000101111101 8
b00000101 9
1:
b00000110 ;
0=
b00000000000000000000000000000001 >
b00000000000000000000000000011101 @
#245000000
0!
0/
#247500000
1!
0,
1/
0:
b00000000000000000000000000000010 >
b00000000000000000000000000011110 @
#250000000
0!
0#
0/
01
#252500000
1!
1/
0<
b00000000000000000000000000000011 >
b00000000000000000000000000011111 @
#255000000
0!
0/
#257500000
1!
1/
b00000000000000000000000000000100 >
b00000000000000000000000000100000 @
#260000000
0!
0/
#262500000
1!
1#
1/
11
1<
1=
b00000000000000000000000000000000 >
b00000000000000000000000000100001 @
#265000000
0!
0/
#267500000
1!
b000000000000000000000000001000010010000101111101 *
b00000110 +
1,
1/
b000000000000000000000000001000010010000101111101 8
b00000110 9
1:
b00000111 ;
0=
b00000000000000000000000000000001 >
b00000000000000000000000000100010 @
#270000000
0!
0/
#272500000
1!
0,
1/
0:
b00000000000000000000000000000010 >
b00000000000000000000000000100011 @
#275000000
0!
0#
0/
01
#277500000
1!
1/
0<
b00000000000000000000000000000011 >
b00000000000000000000000000100100 @
#280000000
0!
0/
#282500000
1!
1/
b00000000000000000000000000000100 >
b00000000000000000000000000100101 @
#285000000
0!
0/
#287500000
1!
1#
1/
11
1<
1=
b00000000000000000000000000000000 >
b00000000000000000000000000100110 @
#290000000
0!
0/
#292500000
1!
b000000000000000000000000001001100010000101111101 *
b00000111 +
1,
1/
b000000000000000000000000001001100010000101111101 8
b00000111 9
1:
b00001000 ;
0=
b00000000000000000000000000000001 >
b00000000000000000000000000100111 @
#295000000
0!
0/
#297500000
1!
0,
1/
0:
b00000000000000000000000000000010 >
b00000000000000000000000000101000 @
#300000000
0!
0#
0/
01
#302500000
1!
1/
0<
b00000000000000000000000000000011 >
b00000000000000000000000000101001 @
#305000000
0!
0/
#307500000
1!
1/
b00000000000000000000000000000100 >
b00000000000000000000000000101010 @
#310000000
0!
0/
#312500000
1!
1#
1/
11
1<
1=
b00000000000000000000000000000000 >
b00000000000000000000000000101011 @
#315000000
0!
0/
#317500000
1!
b000000000000000000000000001010110010000101111101 *
b00001000 +
1,
1/
b000000000000000000000000001010110010000101111101 8
b00001000 9
1:
b00001001 ;
0=
b00000000000000000000000000000001 >
b00000000000000000000000000101100 @
#320000000
0!
0/
#322500000
1!
0,
1/
0:
b00000000000000000000000000000010 >
b00000000000000000000000000101101 @
#325000000
0!
0#
0/
01
#327500000
1!
1/
0<
b00000000000000000000000000000011 >
b00000000000000000000000000101110 @
#330000000
0!
0/
#332500000
1!
1/
b00000000000000000000000000000100 >
b00000000000000000000000000101111 @
#335000000
0!
0/
#337500000
1!
1#
1/
11
1<
1=
b00000000000000000000000000000000 >
b00000000000000000000000000110000 @
#340000000
0!
0/
#342500000
1!
b000000000000000000000000001100000010000101111101 *
b00001001 +
1,
1/
b000000000000000000000000001100000010000101111101 8
b00001001 9
1:
b00001010 ;
0=
b00000000000000000000000000000001 >
b00000000000000000000000000110001 @
#345000000
0!
0/
#347500000
1!
0,
1/
0:
b00000000000000000000000000000010 >
b00000000000000000000000000110010 @
#350000000
0!
0#
0/
01
#352500000
1!
1/
0<
b00000000000000000000000000000011 >
b00000000000000000000000000110011 @
#355000000
0!
0/
#357500000
1!
1/
b00000000000000000000000000000100 >
b00000000000000000000000000110100 @
#360000000
0!
0/
#362500000
1!
1#
1/
11
1<
1=
b00000000000000000000000000000000 >
b00000000000000000000000000110101 @
#365000000
0!
0/
#367500000
1!
b000000000000000000000000001101010010000101111101 *
b00001010 +
1,
1/
b000000000000000000000000001101010010000101111101 8
b00001010 9
1:
b00001011 ;
0=
b00000000000000000000000000000001 >
b00000000000000000000000000110110 @
#370000000
0!
0/
#372500000
1!
0,
1/
0:
b00000000000000000000000000000010 >
b00000000000000000000000000110111 @
#375000000
0!
0#
0/
01
#377500000
1!
1/
0<
b00000000000000000000000000000011 >
b00000000000000000000000000111000 @
#380000000
0!
0/
#382500000
1!
1/
b00000000000000000000000000000100 >
b00000000000000000000000000111001 @
#385000000
0!
0/
#387500000
1!
1#
1/
11
1<
1=
b00000000000000000000000000000000 >
b00000000000000000000000000111010 @
#390000000
0!
0/
#392500000
1!
b000000000000000000000000001110100010000101111101 *
b00001011 +
1,
1/
b000000000000000000000000001110100010000101111101 8
b00001011 9
1:
b00001100 ;
0=
b00000000000000000000000000000001 >
b00000000000000000000000000111011 @
#395000000
0!
0/
#397500000
1!
0,
1/
0:
b00000000000000000000000000000010 >
b00000000000000000000000000111100 @
#400000000
0!
0#
0&
0/
01
04
#402500000
1!
1/
0<
b00000000000000000000000000000011 >
b00000000000000000000000000111101 @
#405000000
0!
0/
#407500000
1!
1/
b00000000000000000000000000000100 >
b00000000000000000000000000111110 @
#410000000
0!
0/
#412500000
1!
1#
1/
11
1<
1=
b00000000000000000000000000000000 >
b00000000000000000000000000111111 @
#415000000
0!
0/
#417500000
1!
0)
b000000000000000000000000001111110000000101111101 *
b00001100 +
1,
1/
07
b000000000000000000000000001111110000000101111101 8
b00001100 9
1:
b00001101 ;
0=
b00000000000000000000000000000001 >
b00000000000000000000000001000000 @
0C
#420000000
0!
1%
0/
13
#422500000
1!
0,
1/
0:
b00000000000000000000000000000010 >
b00000000000000000000000001000001 @
#425000000
0!
0#
0/
01
#427500000
1!
1/
0<
b00000000000000000000000000000011 >
b00000000000000000000000001000010 @
#430000000
0!
0/
#432500000
1!
1/
b00000000000000000000000000000100 >
b00000000000000000000000001000011 @
#435000000
0!
0/
#437500000
1!
1#
1/
11
1<
1=
b00000000000000000000000000000000 >
b00000000000000000000000001000100 @
#440000000
0!
1$
0%
0/
12
03
#442500000
1!
1'
b000000000000000000000000010001001000000101111101 *
b00001101 +
1,
1/
15
b000000000000000000000000010001001000000101111101 8
b00001101 9
1:
b00001110 ;
0=
b00000000000000000000000000000001 >
b00000000000000000000000001000101 @
1A
#445000000
0!
0/
#447500000
1!
0,
1/
0:
b00000000000000000000000000000010 >
b00000000000000000000000001000110 @
#450000000
0!
0#
0/
01
#452500000
1!
1/
0<
b00000000000000000000000000000011 >
b00000000000000000000000001000111 @
#455000000
0!
0/
#457500000
1!
1/
b00000000000000000000000000000100 >
b00000000000000000000000001001000 @
#460000000
0!
0$
1%
0/
02
13
#462500000
1!
1#
1/
11
1<
1=
b00000000000000000000000000000000 >
b00000000000000000000000001001001 @
#465000000
0!
0/
#467500000
1!
0'
1(
b000000000000000000000000010010010100000101111101 *
b00001110 +
1,
1/
05
16
b000000000000000000000000010010010100000101111101 8
b00001110 9
1:
b00001111 ;
0=
b00000000000000000000000000000001 >
b00000000000000000000000001001010 @
0A
1B
#470000000
0!
0/
#472500000
1!
0,
1/
0:
b00000000000000000000000000000010 >
b00000000000000000000000001001011 @
#475000000
0!
0#
0/
01
#477500000
1!
1/
0<
b00000000000000000000000000000011 >
b00000000000000000000000001001100 @
#480000000
0!
1$
0%
0/
12
03
#482500000
1!
1/
b00000000000000000000000000000100 >
b00000000000000000000000001001101 @
#485000000
0!
0/
#487500000
1!
1#
1/
11
1<
1=
b00000000000000000000000000000000 >
b00000000000000000000000001001110 @
#490000000
0!
0/
#492500000
1!
1'
0(
b000000000000000000000000010011101000000101111101 *
b00001111 +
1,
1/
15
06
b000000000000000000000000010011101000000101111101 8
b00001111 9
1:
b00010000 ;
0=
b00000000000000000000000000000001 >
b00000000000000000000000001001111 @
1A
0B
#495000000
0!
0/
#497500000
1!
0,
1/
0:
b00000000000000000000000000000010 >
b00000000000000000000000001010000 @
#500000000
0!
0#
0/
01
#502500000
1!
1/
0<
b00000000000000000000000000000011 >
b00000000000000000000000001010001 @
#505000000
0!
0/
#507500000
1!
1/
b00000000000000000000000000000100 >
b00000000000000000000000001010010 @
#510000000
0!
0/
#512500000
1!
1#
1/
11
1<
1=
b00000000000000000000000000000000 >
b00000000000000000000000001010011 @
#515000000
0!
0/
#517500000
1!
b000000000000000000000000010100111000000101111101 *
b00010000 +
1,
1/
b000000000000000000000000010100111000000101111101 8
b00010000 9
1:
b00010001 ;
0=
b00000000000000000000000000000001 >
b00000000000000000000000001010100 @
#520000000
0!
0$
1%
0/
02
13
#522500000
1!
0,
1/
0:
b00000000000000000000000000000010 >
b00000000000000000000000001010101 @
#525000000
0!
0#
0/
01
#527500000
1!
1/
0<
b00000000000000000000000000000011 >
b00000000000000000000000001010110 @
#530000000
0!
0/
#532500000
1!
1/
b00000000000000000000000000000100 >
b00000000000000000000000001010111 @
#535000000
0!
0/
#537500000
1!
1#
1/
11
1<
1=
b00000000000000000000000000000000 >
b00000000000000000000000001011000 @
#540000000
0!
1$
0%
0/
12
03
#542500000
1!
b000000000000000000000000010110001000000101111101 *
b00010001 +
1,
1/
b000000000000000000000000010110001000000101111101 8
b00010001 9
1:
b00010010 ;
0=
b00000000000000000000000000000001 >
b00000000000000000000000001011001 @
#545000000
0!
0/
#547500000
1!
0,
1/
0:
b00000000000000000000000000000010 >
b00000000000000000000000001011010 @
#550000000
0!
0#
0/
01
#552500000
1!
1/
0<
b00000000000000000000000000000011 >
b00000000000000000000000001011011 @
#555000000
0!
0/
#557500000
1!
1/
b00000000000000000000000000000100 >
b00000000000000000000000001011100 @
#560000000
0!
0$
1%
0/
02
13
#562500000
1!
1#
1/
11
1<
1=
b00000000000000000000000000000000 >
b00000000000000000000000001011101 @
#565000000
0!
0/
#567500000
1!
0'
1(
b000000000000000000000000010111010100000101111101 *
b00010010 +
1,
1/
05
16
b000000000000000000000000010111010100000101111101 8
b00010010 9
1:
b00010011 ;
0=
b00000000000000000000000000000001 >
b00000000000000000000000001011110 @
0A
1B
#570000000
0!
0/
#572500000
1!
0,
1/
0:
b00000000000000000000000000000010 >
b00000000000000000000000001011111 @
#575000000
0!
0#
0/
01
#577500000
1!
1/
0<
b00000000000000000000000000000011 >
b00000000000000000000000001100000 @
#580000000
0!
1&
0/
14
#582500000
1!
1/
b00000000000000000000000000000100 >
b00000000000000000000000001100001 @
#585000000
0!
0/
#587500000
1!
1#
1/
11
1<
1=
b00000000000000000000000000000000 >
b00000000000000000000000001100010 @
#590000000
0!
0/
#592500000
1!
1)
b000000000000000000000000011000100110000101111101 *
b00010011 +
1,
1/
17
b000000000000000000000000011000100110000101111101 8
b00010011 9
1:
b00010100 ;
0=
b00000000000000000000000000000001 >
b00000000000000000000000001100011 @
1C
#595000000
0!
0/
#597500000
1!
0,
1/
0:
b00000000000000000000000000000010 >
b00000000000000000000000001100100 @
#600000000
0!
0#
0/
01
#602500000
1!
1/
0<
b00000000000000000000000000000011 >
b00000000000000000000000001100101 @
#605000000
0!
0/
#607500000
1!
1/
b00000000000000000000000000000100 >
b00000000000000000000000001100110 @
#610000000
0!
0/
#612500000
1!
1#
1/
11
1<
1=
b00000000000000000000000000000000 >
b00000000000000000000000001100111 @
#615000000
0!
0/
